mobobob/.__init__.py.un~
mobobob/__init__.py
mobobob-0.5.1.dist-info/WHEEL
mobobob-0.5.1.dist-info/METADATA
mobobob-0.5.1.dist-info/RECORD
