Metadata-Version: 1.2
Name: mobobob
Version: 0.5.1
Summary: An alias for matplotlib
Home-page: https://github.com/Carreau/mobobob
License: UNKNOWN
Author: Matthias Bussonnier
Author-email: bussonniermatthias@gmail.com
Requires-Python: >=3.4
Classifier: License :: OSI Approved :: MIT License
Requires-Dist: matplotlib
